funciones_prueba/__init__.py
funciones_prueba/func_objetivo.py
metod_multivariable/metodos_directos.py
metod_multivariable/metodos_gradiente.py
metod_univariable/metodos_basado_derivada.py
metod_univariable/metodos_elim_regiones.py
Paqueteria_Optimizacion_byzamm079-0.0.1.dist-info/LICENSE
Paqueteria_Optimizacion_byzamm079-0.0.1.dist-info/METADATA
Paqueteria_Optimizacion_byzamm079-0.0.1.dist-info/WHEEL
Paqueteria_Optimizacion_byzamm079-0.0.1.dist-info/top_level.txt
Paqueteria_Optimizacion_byzamm079-0.0.1.dist-info/RECORD
